collibra_catalog/__init__.py
collibra_catalog/api_client.py
collibra_catalog/configuration.py
collibra_catalog/rest.py
collibra_catalog/api/__init__.py
collibra_catalog/api/jdbc_schema_ingestion_api.py
collibra_catalog/api/job_server_instance_configuration_api.py
collibra_catalog/models/__init__.py
collibra_catalog/models/add_schema_from_jdbc_request.py
collibra_catalog/models/job.py
collibra_catalog/models/job_server_instance.py
collibra_catalog/models/job_server_instance_response.py
collibra_catalog/models/paged_response_job_server_instance.py
collibra_catalog/models/refresh_jdbc_schema_request.py
test/__init__.py
test/test_add_schema_from_jdbc_request.py
test/test_jdbc_schema_ingestion_api.py
test/test_job.py
test/test_job_server_instance.py
test/test_job_server_instance_configuration_api.py
test/test_job_server_instance_response.py
test/test_paged_response_job_server_instance.py
test/test_refresh_jdbc_schema_request.py
collibra_catalog_100-1.0.0.dist-info/METADATA
collibra_catalog_100-1.0.0.dist-info/WHEEL
collibra_catalog_100-1.0.0.dist-info/top_level.txt
collibra_catalog_100-1.0.0.dist-info/RECORD
